MANIFEST.in
README.txt
setup.py
docs/CREDITS.txt
docs/HISTORY.txt
docs/LICENSE.txt
src/silva/__init__.py
src/silva.app.news.egg-info/PKG-INFO
src/silva.app.news.egg-info/SOURCES.txt
src/silva.app.news.egg-info/dependency_links.txt
src/silva.app.news.egg-info/entry_points.txt
src/silva.app.news.egg-info/namespace_packages.txt
src/silva.app.news.egg-info/not-zip-safe
src/silva.app.news.egg-info/requires.txt
src/silva.app.news.egg-info/top_level.txt
src/silva/app/__init__.py
src/silva/app/news/NewsCategorization.py
src/silva/app/news/NewsPublication.py
src/silva/app/news/ServiceNews.py
src/silva/app/news/ServiceNewsCategorization.py
src/silva/app/news/Tree.py
src/silva/app/news/__init__.py
src/silva/app/news/configure.zcml
src/silva/app/news/datetimeutils.py
src/silva/app/news/ftesting.zcml
src/silva/app/news/htmlcalendar.py
src/silva/app/news/indexing.py
src/silva/app/news/installer.py
src/silva/app/news/interfaces.py
src/silva/app/news/snn-np-settings.xml
src/silva/app/news/testing.py
src/silva/app/news/upgrade.py
src/silva/app/news/AgendaItem/__init__.py
src/silva/app/news/AgendaItem/content.py
src/silva/app/news/AgendaItem/smi.py
src/silva/app/news/AgendaItem/views.py
src/silva/app/news/AgendaItem/static/ical.png
src/silva/app/news/AgendaItem/views_templates/agendaitemlistitemview.cpt
src/silva/app/news/AgendaItem/views_templates/agendaitemview.cpt
src/silva/app/news/NewsItem/__init__.py
src/silva/app/news/NewsItem/content.py
src/silva/app/news/NewsItem/smi.py
src/silva/app/news/NewsItem/views.py
src/silva/app/news/NewsItem/smi_templates/newsitempublicationportlet.cpt
src/silva/app/news/NewsItem/views_templates/newsitemlistitemview.cpt
src/silva/app/news/NewsItem/views_templates/newsitemview.cpt
src/silva/app/news/ServiceNews_templates/manageservicenews.pt
src/silva/app/news/adapters/__init__.py
src/silva/app/news/adapters/feed.py
src/silva/app/news/adapters/feedentry.py
src/silva/app/news/adapters/ical.py
src/silva/app/news/adapters/feed_templates/atom.pt
src/silva/app/news/adapters/feed_templates/rss.pt
src/silva/app/news/codesources/__init__.py
src/silva/app/news/codesources/api.py
src/silva/app/news/codesources/inline.py
src/silva/app/news/codesources/cs_inline_viewer/parameters.xml
src/silva/app/news/codesources/cs_inline_viewer/render_viewer.pt
