Metadata-Version: 1.1
Name: silva.app.news
Version: 3.0.4
Summary: News extension for Silva 3
Home-page: https://github.com/silvacms/silva.app.news
Author: Infrae
Author-email: info@infrae.com
License: BSD
Keywords: news silva zope2
Platform: UNKNOWN
Classifier: Framework :: Zope2
Classifier: Topic :: Internet :: WWW/HTTP :: Dynamic Content :: Message Boards
Classifier: Programming Language :: Python
Classifier: Topic :: Software Development :: Libraries :: Python Modules
